RAI/__init__.py
RAI/data_collector.py
RAI/demos.py
RAI/launcher.py
RAI/main_window.py
RAI/plotting.py
RAI/sensors.py
RAI/serial.py
RAI/session.py
RAI/slider.py
RAI/table.py
RAI/timers.py
RAI/utils.py
RAI/version.py
RAI/video.py
RAI/view.py
RAI/resources/bolt.mp4
RAI/resources/d00300
RAI/resources/demo_data.npz
RAI/resources/session_demo.json
RAI/resources/solo.mp4
RAI/resources/jviereck_hopper/recording.mp4
RAI/resources/jviereck_hopper/traj.pkl
RAI/static/icon.png
robot_analysis_interface-1.0.data/scripts/rai
robot_analysis_interface-1.0.dist-info/METADATA
robot_analysis_interface-1.0.dist-info/WHEEL
robot_analysis_interface-1.0.dist-info/top_level.txt
robot_analysis_interface-1.0.dist-info/RECORD
