Metadata-Version: 2.1
Name: robot-analysis-interface
Version: 1.0
Summary: Robot Analysis Infrastructure
Home-page: https://gitlab.tuebingen.mpg.de/SoW/amd-robot-plotting-framework
Author: Jean-Claude Passy, Maximilien Naveau
Author-email: jean-claude.passy@tuebingen.mpg.de, maximilien.naveau@tuebingen.mpg.de
License: BSD-3-Clause
Project-URL: Documentation, https://machines-in-motion.github.io/code_documentation/amd-robot-plotting-framework/docs/sphinx/html/index.html
Platform: Linux
Classifier: License :: OSI Approved :: BSD License
Classifier: Programming Language :: Python
Classifier: Programming Language :: Python :: 3
Classifier: Programming Language :: Python :: 3 :: Only
Classifier: Programming Language :: Python :: 3.6
Classifier: Programming Language :: Python :: 3.7
Classifier: Programming Language :: Python :: 3.8
Classifier: Programming Language :: Python :: 3.9
Requires-Python: >=3.6
Requires-Dist: numpy
Requires-Dist: opencv-python (==4.3.0.36)
Requires-Dist: packaging
Requires-Dist: PyQt5
Requires-Dist: pyqtgraph (==0.11.0)
Requires-Dist: qimage2ndarray
